djangodeployer/__init__.py
djangodeployer/cmd_listener.py
djangodeployer/installer.py
djangodeployer-0.1.0.dist-info/METADATA
djangodeployer-0.1.0.dist-info/WHEEL
djangodeployer-0.1.0.dist-info/entry_points.txt
djangodeployer-0.1.0.dist-info/top_level.txt
djangodeployer-0.1.0.dist-info/RECORD
