Metadata-Version: 2.1
Name: djangodeployer
Version: 0.1.0
Summary: Deploy django project
Home-page: UNKNOWN
Author: Hristo Mavrodiev
Author-email: h.mavrodiev@abv.bg
License: UNKNOWN
Platform: UNKNOWN
